legacy/__init__.py
legacy/analyze_final_report.py
legacy/analyze_using_bayes_autocpt.py
legacy/architecture.py
legacy/datasets.py
legacy/evaluation_on_simulated_150mers.py
legacy/evaluation_on_simulated_50mers.py
legacy/evaluation_on_simulated_HIV.py
legacy/generate_report.py
legacy/predict_100mers.py
legacy/predict_50mers.py
legacy/predict_on_realdata.py
legacy/preprocessing.py
legacy/training_model.py
legacy/utils.py
legacy/voting.py
legacy/wandb.py
metagentools/__init__.py
metagentools/_modidx.py
metagentools/art.py
metagentools/bio.py
metagentools/core.py
metagentools/wandb.py
metagentools/cnn_virus/__init__.py
metagentools/cnn_virus/architecture.py
metagentools/cnn_virus/data.py
metagentools/cnn_virus/utils.py
metagentools-0.0.10.dist-info/LICENSE
metagentools-0.0.10.dist-info/METADATA
metagentools-0.0.10.dist-info/WHEEL
metagentools-0.0.10.dist-info/entry_points.txt
metagentools-0.0.10.dist-info/top_level.txt
metagentools-0.0.10.dist-info/RECORD
