Metadata-Version: 2.1
Name: metagentools
Version: 0.0.10
Summary: Set of tools used for metagenomics research project
Home-page: https://github.com/vtecftwy/metagentools
Author: Charlier
Author-email: github@procurasia.com
License: Apache Software License 2.0
Keywords: nbdev jupyter notebook python
Classifier: Development Status :: 4 - Beta
Classifier: Intended Audience :: Science/Research
Classifier: Natural Language :: English
Classifier: Programming Language :: Python :: 3.8
Classifier: Programming Language :: Python :: 3.9
Classifier: Programming Language :: Python :: 3.10
Classifier: License :: OSI Approved :: Apache Software License
Requires-Python: >=3.8
License-File: LICENSE
Requires-Dist: fastcore
Requires-Dist: numpy
Requires-Dist: pandas
Requires-Dist: tensorflow
Requires-Dist: tqdm
Requires-Dist: wandb
Requires-Dist: ecutilities
Provides-Extra: dev
Requires-Dist: nbdev ; extra == 'dev'
